nosqueel.py
nosqueel-0.1.2.dist-info/LICENSE
nosqueel-0.1.2.dist-info/METADATA
nosqueel-0.1.2.dist-info/WHEEL
nosqueel-0.1.2.dist-info/RECORD
